deepfusion/__init__.py
deepfusion/components/__init__.py
deepfusion/components/data/__init__.py
deepfusion/components/data/data.py
deepfusion/components/data/regularizers.py
deepfusion/components/modules/__init__.py
deepfusion/components/modules/add.py
deepfusion/components/modules/conv2d.py
deepfusion/components/modules/flatten.py
deepfusion/components/modules/matmul.py
deepfusion/components/modules/module.py
deepfusion/components/modules/activation_functions/__init__.py
deepfusion/components/modules/activation_functions/elu.py
deepfusion/components/modules/activation_functions/lrelu.py
deepfusion/components/modules/activation_functions/prelu.py
deepfusion/components/modules/activation_functions/relu.py
deepfusion/components/modules/activation_functions/sigmoid.py
deepfusion/components/modules/activation_functions/tanh.py
deepfusion/components/modules/dropout/__init__.py
deepfusion/components/modules/dropout/dropout.py
deepfusion/components/modules/dropout/inverted_dropout.py
deepfusion/components/modules/loss_functions/__init__.py
deepfusion/components/modules/loss_functions/cross_entropy.py
deepfusion/components/modules/loss_functions/logistic.py
deepfusion/components/modules/loss_functions/mse.py
deepfusion/components/modules/loss_functions/sum_loss.py
deepfusion/components/modules/normalizations/__init__.py
deepfusion/components/modules/normalizations/batch_norm.py
deepfusion/components/modules/normalizations/layer_norm.py
deepfusion/components/modules/pooling/__init__.py
deepfusion/components/modules/pooling/maxpool.py
deepfusion/components/modules/rnn/__init__.py
deepfusion/components/modules/rnn/rnn1.py
deepfusion/components/modules/rnn/rnn2.py
deepfusion/components/modules/utils/__init__.py
deepfusion/components/modules/utils/functions.py
deepfusion/components/net/__init__.py
deepfusion/components/net/net.py
deepfusion/components/optimizers/__init__.py
deepfusion/components/optimizers/adagrad.py
deepfusion/components/optimizers/adam.py
deepfusion-0.0.3.dist-info/LICENSE
deepfusion-0.0.3.dist-info/METADATA
deepfusion-0.0.3.dist-info/WHEEL
deepfusion-0.0.3.dist-info/top_level.txt
deepfusion-0.0.3.dist-info/RECORD
