Metadata-Version: 2.1
Name: deepfusion
Version: 0.0.3
Summary: DeepFusion is a highly modular and customizable deep learning framework!
Home-page: https://github.com/atharvaaalok/deepfusion
Author: Atharva Aalok
Author-email: atharvaaalok@gmail.com
License: MIT
Keywords: deepfusion,deep learning,neural networks,artificial intelligence,machine learning,model,optimization,backpropagation
License-File: LICENSE
Requires-Dist: numpy ==1.26.4
Requires-Dist: matplotlib ==3.8.4
Requires-Dist: setuptools ==69.5.1
Requires-Dist: typing-extensions ==4.11.0
Provides-Extra: gpu
Requires-Dist: cupy-cuda12x ==13.1.0 ; extra == 'gpu'
Provides-Extra: visualization
Requires-Dist: graphviz ==0.20.3 ; extra == 'visualization'
